sphinx_bioschemas/__init__.py
sphinx_bioschemas-0.1.1.dist-info/licenses/LICENSE
sphinx_bioschemas-0.1.1.dist-info/METADATA
sphinx_bioschemas-0.1.1.dist-info/WHEEL
sphinx_bioschemas-0.1.1.dist-info/top_level.txt
sphinx_bioschemas-0.1.1.dist-info/RECORD
